{
  "name": "Comment",
  "base": "PersistedModel",
  "idInjection": true,
  "options": {
    "validateUpsert": true
  },
  "properties": {
    "Text": {
      "type": "string",
      "required": true
    },
    "Time": {
      "type": "date"
    }
  },
  "validations": [],
  "relations": {
    "Contributor": {
      "type": "belongsTo",
      "model": "UserProfile",
      "foreignKey": "userProfileId"
    },
    "InReferenceTo": {
      "type": "belongsTo",
      "model": "Comment",
      "foreignKey": ""
    }
  },
  "acls": [],
  "methods": {}
}
